DataValuationPlatform/__init__.py
DataValuationPlatform/Datasets/GPCR/GPCR_train.csv
DataValuationPlatform/Datasets/GPCR/GPCR_val.csv
DataValuationPlatform/Datasets/GPCR_2/GPCR_2_train.csv
DataValuationPlatform/Datasets/GPCR_2/GPCR_2_val.csv
DataValuationPlatform/Datasets/GPCR_3/GPCR_3_train.csv
DataValuationPlatform/Datasets/GPCR_3/GPCR_3_val.csv
DataValuationPlatform/Datasets/RNA_binding/RNA_binding_train.csv
DataValuationPlatform/Datasets/RNA_binding/RNA_binding_val.csv
DataValuationPlatform/Datasets/channel_atp/channel_atp_train.csv
DataValuationPlatform/Datasets/channel_atp/channel_atp_val.csv
DataValuationPlatform/Datasets/cysteine_protease/cysteine_protease_train.csv
DataValuationPlatform/Datasets/cysteine_protease/cysteine_protease_val.csv
DataValuationPlatform/Datasets/dna_repair/dna_repair_train.csv
DataValuationPlatform/Datasets/dna_repair/dna_repair_val.csv
DataValuationPlatform/Datasets/fatty_acid_synthase/fatty_acid_synthase_train.csv
DataValuationPlatform/Datasets/fatty_acid_synthase/fatty_acid_synthase_val.csv
DataValuationPlatform/Datasets/hsf1/hsf1_train.csv
DataValuationPlatform/Datasets/hsf1/hsf1_val.csv
DataValuationPlatform/Datasets/ion_channel/ion_channel_train.csv
DataValuationPlatform/Datasets/ion_channel/ion_channel_val.csv
DataValuationPlatform/Datasets/ion_channel2/ion_channel2_train.csv
DataValuationPlatform/Datasets/ion_channel2/ion_channel2_val.csv
DataValuationPlatform/Datasets/ion_channel3/ion_channel3_train.csv
DataValuationPlatform/Datasets/ion_channel3/ion_channel3_val.csv
DataValuationPlatform/Datasets/methylation/methylation_train.csv
DataValuationPlatform/Datasets/methylation/methylation_val.csv
DataValuationPlatform/Datasets/serine/serine_train.csv
DataValuationPlatform/Datasets/serine/serine_val.csv
DataValuationPlatform/Datasets/splicing/splicing_train.csv
DataValuationPlatform/Datasets/splicing/splicing_val.csv
DataValuationPlatform/Datasets/streptokinase/streptokinase_train.csv
DataValuationPlatform-1.3.dist-info/LICENSE
DataValuationPlatform-1.3.dist-info/METADATA
DataValuationPlatform-1.3.dist-info/WHEEL
DataValuationPlatform-1.3.dist-info/top_level.txt
DataValuationPlatform-1.3.dist-info/RECORD
