Metadata-Version: 2.1
Name: DataValuationPlatform
Version: 1.3
Summary: A modular platform to test data valuation methods on High Throughput Screen data applications
Home-page: https://github.com/JoshuaHesse/DataValuationPlatform
Author: Joshua Hesse
Author-email: joshua.hesse@tum.de
License: UNKNOWN
Platform: UNKNOWN
Requires-Python: ==3.8.*
Requires-Dist: chembl-structure-pipeline (==1.2.0)
Requires-Dist: gpflow (==2.8.0)
Requires-Dist: imbalanced-learn (==0.10.1)
Requires-Dist: jupyter
Requires-Dist: ipykernel
Requires-Dist: matplotlib (==3.6.0)
Requires-Dist: pandas (==1.4.0)
Requires-Dist: rdkit (==2022.9.5)
Requires-Dist: scikit-learn (==1.2.2)
Requires-Dist: scipy (==1.8.1)
Requires-Dist: tensorflow (==2.4.0)
Requires-Dist: tensorflow-probability (==0.12.1)
Requires-Dist: tqdm (==4.60.0)
Requires-Dist: lightgbm (==3.3.5)
Requires-Dist: catboost (==1.1.1)
